[
    {
        "descripcion": "Detergente para ropa Floral",
        "precioVenta": 55.00,
        "codigo": "DET00001",
        "categoria": "Detergentes",
        "medida": "4 Litros"
    },
    {
        "descripcion": "Detergente para ropa Floral",
        "precioVenta": 175.00,
        "codigo": "DET00002",
        "categoria": "Detergentes",
        "medida": "20 Litros"
    },
    {
        "descripcion": "Detergente para ropa Manzana Verde",
        "precioVenta": 55.00,
        "codigo": "DET00003",
        "categoria": "Detergentes",
        "medida": "4 Litros"
    },
    {
        "descripcion": "Detergente para ropa Manzana Verde",
        "precioVenta": 175.00,
        "codigo": "DET00004",
        "categoria": "Detergentes",
        "medida": "20 Litros"
    },
    {
        "descripcion": "Detergente para ropa Naranja",
        "precioVenta": 55.00,
        "codigo": "DET00005",
        "categoria": "Detergentes",
        "medida": "4 Litros"
    },
    {
        "descripcion": "Detergente para ropa Naranja",
        "precioVenta": 175.00,
        "codigo": "DET00006",
        "categoria": "Detergentes",
        "medida": "20 Litros"
    },
    {
        "descripcion": "Jabón líquido para trastes",
        "precioVenta": 17.50,
        "codigo": "JAB00001",
        "categoria": "Jabones",
        "medida": "1 Litro"
    },
    {
        "descripcion": "Jabón líquido para trastes",
        "precioVenta": 45.00,
        "codigo": "JAB00002",
        "categoria": "Jabones",
        "medida": "4 Litros"
    },
    {
        "descripcion": "Suavizante para telas Flor de Manzana",
        "precioVenta": 70.00,
        "codigo": "SUA00001",
        "categoria": "Suavizantes",
        "medida": "4 Litros"
    },
    {
        "descripcion": "Suavizante para telas Flor de Manzana",
        "precioVenta": 210.00,
        "codigo": "SUA00002",
        "categoria": "Suavizantes",
        "medida": "20 Litros"
    },
    {
        "descripcion": "Suavizante para telas Fresca Primavera",
        "precioVenta": 70.00,
        "codigo": "SUA00003",
        "categoria": "Suavizantes",
        "medida": "4 Litros"
    },
    {
        "descripcion": "Suavizante para telas Fresca Primavera",
        "precioVenta": 210.00,
        "codigo": "SUA00004",
        "categoria": "Suavizantes",
        "medida": "20 Litros"
    },
    {
        "descripcion": "Suavizante para telas Suave Caricia",
        "precioVenta": 75.00,
        "codigo": "SUA00005",
        "categoria": "Suavizantes",
        "medida": "4 Litros"
    },
    {
        "descripcion": "Suavizante para telas Suave Caricia",
        "precioVenta": 225.00,
        "codigo": "SUA00006",
        "categoria": "Suavizantes",
        "medida": "20 Litros"
    },
    {
        "descripcion": "Shampoo Vainilla Y Caramelo",
        "precioVenta": 45.00,
        "codigo": "CUI00001",
        "categoria": "Cuidado Personal",
        "medida": "450 ml"
    },
    {
        "descripcion": "Shampoo Vainilla Y Caramelo",
        "precioVenta": 100.00,
        "codigo": "CUI00002",
        "categoria": "Cuidado Personal",
        "medida": "1000 ml"
    },
    {
        "descripcion": "Acondicionador para Cabello Caramelo",
        "precioVenta": 55.00,
        "codigo": "CUI00003",
        "categoria": "Cuidado Personal",
        "medida": "450 ml"
    },
    {
        "descripcion": "Acondicionador para Cabello Fresa Mora",
        "precioVenta": 55.00,
        "codigo": "CUI00004",
        "categoria": "Cuidado Personal",
        "medida": "450 ml"
    },
    {
        "descripcion": "Acondicionador para Cabello Cereza",
        "precioVenta": 55.00,
        "codigo": "CUI00005",
        "categoria": "Cuidado Personal",
        "medida": "450 ml"
    },
    {
        "descripcion": "Jabón líquido para manos Fresa Mora",
        "precioVenta": 40.00,
        "codigo": "CUI00006",
        "categoria": "Cuidado Personal",
        "medida": "450 ml"
    },
    {
        "descripcion": "Jabón líquido para manos Vainilla y Caramelo",
        "precioVenta": 40.00,
        "codigo": "CUI00007",
        "categoria": "Cuidado Personal",
        "medida": "450 ml"
    },
    {
        "descripcion": "Jabón líquido para manos Cereza",
        "precioVenta": 40.00,
        "codigo": "CUI00008",
        "categoria": "Cuidado Personal",
        "medida": "450 ml"
    },
    {
        "descripcion": "Toallas Microfibra 30x30 cm",
        "precioVenta": 20.00,
        "codigo": "LIH00001",
        "categoria": "Limpieza del Hogar",
        "medida": "Paquete de 2"
    },
    {
        "descripcion": "Cepillo para Lavar Trastes",
        "precioVenta": 15.00,
        "codigo": "ACL00001",
        "categoria": "Accesorios de Limpieza",
        "medida": "Unidad"
    },
    {
        "descripcion": "Esponja Scotch-Brite Multisuperficies",
        "precioVenta": 12.50,
        "codigo": "ACL00002",
        "categoria": "Accesorios de Limpieza",
        "medida": "Unidad"
    },
    {
        "descripcion": "Esponja Doble Uso (Suave y Abrasiva)",
        "precioVenta": 10.00,
        "codigo": "ACL00003",
        "categoria": "Accesorios de Limpieza",
        "medida": "3 unidades"
    },
    {
        "descripcion": "Detergente en Polvo Limón",
        "precioVenta": 75.00,
        "codigo": "DET00007",
        "categoria": "Detergentes",
        "medida": "5 Kg"
    },
    {
        "descripcion": "Limpiador Multiusos Floral",
        "precioVenta": 30.00,
        "codigo": "LIH00002",
        "categoria": "Limpieza del Hogar",
        "medida": "1 Litro"
    },
    {
        "descripcion": "Jabón Líquido Antibacterial Manos",
        "precioVenta": 25.00,
        "codigo": "CUI00009",
        "categoria": "Cuidado Personal",
        "medida": "500 ml"
    },
    {
        "descripcion": "Ambientador Aroma Lavanda",
        "precioVenta": 20.00,
        "codigo": "ARO00001",
        "categoria": "Aromatizantes",
        "medida": "300 ml"
    },
    {
        "descripcion": "Limpiador de Vidrios con Alcohol",
        "precioVenta": 28.00,
        "codigo": "LIH00003",
        "categoria": "Limpieza del Hogar",
        "medida": "750 ml"
    },
    {
        "descripcion": "Desinfectante Pino Concentrado",
        "precioVenta": 35.00,
        "codigo": "LIH00004",
        "categoria": "Limpieza del Hogar",
        "medida": "1 Litro"
    },
        {
        "descripcion": "Detergente Líquido Lavanda",
        "precioVenta": 82.50,
        "codigo": "DET00008",
        "categoria": "Detergentes",
        "medida": "4 Litros" 
    },
    {
        "descripcion": "Envase oval nacarado, tapa flip top natural",
        "precioVenta": 2.95,
        "codigo": "ENV00001",
        "categoria": "Envases",
        "medida": "400 ml, Unidad"
    },
    {
        "descripcion": "Envase capitech morado, tapa flip top natural",
        "precioVenta": 2.90,
        "codigo": "ENV00002",
        "categoria": "Envases",
        "medida": "400 ml, Unidad"
    },
    {
        "descripcion": "Envase capitech negro, tapa flip top natural",
        "precioVenta": 2.90,
        "codigo": "ENV00003",
        "categoria": "Envases",
        "medida": "400 ml, Unidad"
    },
    {
        "descripcion": "Envase capitech blanco, tapa flip top natural",
        "precioVenta": 2.90,
        "codigo": "ENV00004",
        "categoria": "Envases",
        "medida": "400 ml, Unidad"
    },
    {
        "descripcion": "Envase pet válvula desenroscable",
        "precioVenta": 2.80,
        "codigo": "ENV00005",
        "categoria": "Envases",
        "medida": "550 ml, Unidad"
    },
    {
        "descripcion": "Envase pet válvula con seguro",
        "precioVenta": 2.80,
        "codigo": "ENV00006",
        "categoria": "Envases",
        "medida": "550 ml, Unidad"
    },
    {
        "descripcion": "Envase pet válvula desenroscable",
        "precioVenta": 3.00,
        "codigo": "ENV00007",
        "categoria": "Envases",
        "medida": "1000 ml, Unidad"
    },
    {
        "descripcion": "Contorneador 02 BISSÚ",
        "precioVenta": 75.00,
        "codigo": "CONT02",
        "categoria": "Cosmetico",
        "medida": "Unidad"
    },
    {
        "descripcion": "Rubor 02 BISSÚ",
        "precioVenta": 45.00,
        "codigo": "RBR02",
        "categoria": "Cosmetico",
        "medida": "Unidad"
    },
    {
        "descripcion": "Iluminador 07 BISSÚ",
        "precioVenta": 45.00,
        "codigo": "PCB07",
        "categoria": "Cosmetico",
        "medida": "Unidad"
    },
    {
        "descripcion": "Sombra Quinteto 11 BISSÚ",
        "precioVenta": 45.00,
        "codigo": "SQ011",
        "categoria": "Cosmetico",
        "medida": "Unidad"
    },
    {
        "descripcion": "Polvo para Párpados 19 BISSÚ",
        "precioVenta": 20.00,
        "codigo": "3310199",
        "categoria": "Cosmetico",
        "medida": "Unidad"
    },
    {
        "descripcion": "Labial 01 Humectante BISSÚ",
        "precioVenta": 29.00,
        "codigo": "01",
        "categoria": "Cosmetico",
        "medida": "Unidad"
    },
    {
        "descripcion": "Labial 18 Humectante BISSÚ",
        "precioVenta": 29.00,
        "codigo": "18",
        "categoria": "Cosmetico",
        "medida": "Unidad"
    },
    {
        "descripcion": "Labial 27 Humectante BISSÚ",
        "precioVenta": 29.00,
        "codigo": "27",
        "categoria": "Cosmetico",
        "medida": "Unidad"
    },
    {
        "descripcion": "Bálsamo Labial Lip Oil Uva Ruby Rose",
        "precioVenta": 32.00,
        "codigo": "BLMU003",
        "categoria": "Cosmetico",
        "medida": "Unidad"
    },
    {
        "descripcion": "Máscara de Pestañas Gris",
        "precioVenta": 32.00,
        "codigo": "23079744",
        "categoria": "Cosmetico",
        "medida": "Unidad"
    },
    {
        "descripcion": "Máscara de Pestañas Negro",
        "precioVenta": 32.00,
        "codigo": "501734",
        "categoria": "Cosmetico",
        "medida": "Unidad"
    },
    {
        "descripcion": "Corrector Líquido 07",
        "precioVenta": 35.00,
        "codigo": "350107",
        "categoria": "Cosmetico",
        "medida": "Unidad"
    },
    {
        "descripcion": "Esponja Maquilladora",
        "precioVenta": 8.00,
        "codigo": "ESP.30",
        "categoria": "Cosmetico",
        "medida": "Unidad"
    },
    {
        "descripcion": "Brocha Maquilladora",
        "precioVenta": 20.00,
        "codigo": "BCHM",
        "categoria": "Cosmetico",
        "medida": "Unidad"
    }
]

